[
  {
    "atomicId": "8a612d61-13e1-4f72-8ad5-c4d411cf0df0",
    "phoneNumber": "12088508796",
    "receivedAt": "2026-02-09T18:00:47+00:00",
    "originalMessage": "STOP",
    "atomicMessage": "STOP",
    "pollId": "019c29d4-81aa-733e-a72a-3983baf19a22",
    "clusterId": "",
    "theme": "Opt Out Request",
    "category": "",
    "summary": "",
    "sentiment": "",
    "isOptOut": true
  },
  {
    "atomicId": "ec9b9775-217a-45e4-a734-d76458ac2f18",
    "phoneNumber": "12085596633",
    "receivedAt": "2026-02-09T18:00:48+00:00",
    "originalMessage": "Stop",
    "atomicMessage": "Stop",
    "pollId": "019c29d4-81aa-733e-a72a-3983baf19a22",
    "clusterId": "",
    "theme": "Opt Out Request",
    "category": "",
    "summary": "",
    "sentiment": "",
    "isOptOut": true
  },
  {
    "atomicId": "d0a91e2d-1e76-4fef-a103-1a03d47b9ee5",
    "phoneNumber": "12088639774",
    "receivedAt": "2026-02-09T18:00:55+00:00",
    "originalMessage": "Traffic",
    "atomicMessage": "The volume and flow of traffic in the local area requires attention to improve mobility and safety.",
    "pollId": "019c29d4-81aa-733e-a72a-3983baf19a22",
    "clusterId": 2,
    "theme": "Traffic Congestion Management",
    "category": "Transportation",
    "summary": "Residents demand immediate action to reduce traffic volume and improve road safety through better infrastructure and enforcement.",
    "sentiment": "negative",
    "isOptOut": false
  },
  {
    "atomicId": "2d552913-edd3-4265-81e4-e358e595a999",
    "phoneNumber": "12087045963",
    "receivedAt": "2026-02-09T18:00:55+00:00",
    "originalMessage": "Stop ",
    "atomicMessage": "Stop ",
    "pollId": "019c29d4-81aa-733e-a72a-3983baf19a22",
    "clusterId": "",
    "theme": "Opt Out Request",
    "category": "",
    "summary": "",
    "sentiment": "",
    "isOptOut": true
  },
  {
    "atomicId": "e4e2f574-323e-4552-8cbd-5154b773d55b",
    "phoneNumber": "12082831220",
    "receivedAt": "2026-02-09T18:01:16+00:00",
    "originalMessage": "Stop",
    "atomicMessage": "Stop",
    "pollId": "019c29d4-81aa-733e-a72a-3983baf19a22",
    "clusterId": "",
    "theme": "Opt Out Request",
    "category": "",
    "summary": "",
    "sentiment": "",
    "isOptOut": true
  },
  {
    "atomicId": "7e7f65ee-8ff6-43f1-9727-c8c66c07685e",
    "phoneNumber": "12088418310",
    "receivedAt": "2026-02-09T18:01:30+00:00",
    "originalMessage": "STOP",
    "atomicMessage": "STOP",
    "pollId": "019c29d4-81aa-733e-a72a-3983baf19a22",
    "clusterId": "",
    "theme": "Opt Out Request",
    "category": "",
    "summary": "",
    "sentiment": "",
    "isOptOut": true
  },
  {
    "atomicId": "15e5b8b7-c197-44fa-8c47-5ebcf55a05b5",
    "phoneNumber": "12084842968",
    "receivedAt": "2026-02-09T18:01:37+00:00",
    "originalMessage": "Stop",
    "atomicMessage": "Stop",
    "pollId": "019c29d4-81aa-733e-a72a-3983baf19a22",
    "clusterId": "",
    "theme": "Opt Out Request",
    "category": "",
    "summary": "",
    "sentiment": "",
    "isOptOut": true
  },
  {
    "atomicId": "4d0c6074-c03b-4afc-8c39-163188ed652a",
    "phoneNumber": "12817265015",
    "receivedAt": "2026-02-09T18:02:01+00:00",
    "originalMessage": "Community development of parks and community engagement opportunities.  That and biking infrastructure that is actually safe ",
    "atomicMessage": "Community development of parks and community engagement opportunities.",
    "pollId": "019c29d4-81aa-733e-a72a-3983baf19a22",
    "clusterId": 8,
    "theme": "Community Safety Enhancements",
    "category": "Community Services",
    "summary": "Residents demand a comprehensive approach to public safety that combines park development with drug prevention and violence reduction.",
    "sentiment": "concerned",
    "isOptOut": false
  },
  {
    "atomicId": "f48ce543-5539-4c6b-91d3-ece10ddba634",
    "phoneNumber": "12817265015",
    "receivedAt": "2026-02-09T18:02:01+00:00",
    "originalMessage": "Community development of parks and community engagement opportunities.  That and biking infrastructure that is actually safe ",
    "atomicMessage": "Biking infrastructure that is actually safe.",
    "pollId": "019c29d4-81aa-733e-a72a-3983baf19a22",
    "clusterId": 0,
    "theme": "Infrastructure Maintenance",
    "category": "Infrastructure",
    "summary": "Residents demand immediate repairs to damaged roadways, safer cycling paths, and better management of invasive weeds on public sidewalks.",
    "sentiment": "negative",
    "isOptOut": false
  },
  {
    "atomicId": "cd8b7a10-0edd-4cba-bfe4-953c7b182eae",
    "phoneNumber": "12082846820",
    "receivedAt": "2026-02-09T18:02:13+00:00",
    "originalMessage": "Slow down growth until our roads can handle it.  Also cost of living inflated by out of staters moving in and driving up our housing costs.",
    "atomicMessage": "Slow down growth until roads in the local area can handle the increased capacity.",
    "pollId": "019c29d4-81aa-733e-a72a-3983baf19a22",
    "clusterId": 2,
    "theme": "Traffic Congestion Management",
    "category": "Transportation",
    "summary": "Residents demand immediate action to reduce traffic volume and improve road safety through better infrastructure and enforcement.",
    "sentiment": "negative",
    "isOptOut": false
  },
  {
    "atomicId": "10707e1d-b073-42e1-aa69-03b3d4a5d704",
    "phoneNumber": "12082846820",
    "receivedAt": "2026-02-09T18:02:13+00:00",
    "originalMessage": "Slow down growth until our roads can handle it.  Also cost of living inflated by out of staters moving in and driving up our housing costs.",
    "atomicMessage": "The cost of living is inflated by new residents moving into the area.",
    "pollId": "019c29d4-81aa-733e-a72a-3983baf19a22",
    "clusterId": 6,
    "theme": "Affordable Housing Expansion",
    "category": "Housing",
    "summary": "Residents demand lower housing costs and rent protections to combat displacement caused by new population growth.",
    "sentiment": "concerned",
    "isOptOut": false
  },
  {
    "atomicId": "67d8b965-2521-47d4-8611-411f60786318",
    "phoneNumber": "12082846820",
    "receivedAt": "2026-02-09T18:02:13+00:00",
    "originalMessage": "Slow down growth until our roads can handle it.  Also cost of living inflated by out of staters moving in and driving up our housing costs.",
    "atomicMessage": "Housing costs are being driven up by increased demand from people moving into the community.",
    "pollId": "019c29d4-81aa-733e-a72a-3983baf19a22",
    "clusterId": 6,
    "theme": "Affordable Housing Expansion",
    "category": "Housing",
    "summary": "Residents demand lower housing costs and rent protections to combat displacement caused by new population growth.",
    "sentiment": "concerned",
    "isOptOut": false
  },
  {
    "atomicId": "e9b2e459-e9cd-4b8f-beb8-93e3d84cc0ef",
    "phoneNumber": "12087945380",
    "receivedAt": "2026-02-09T18:02:24+00:00",
    "originalMessage": "STOP",
    "atomicMessage": "STOP",
    "pollId": "019c29d4-81aa-733e-a72a-3983baf19a22",
    "clusterId": "",
    "theme": "Opt Out Request",
    "category": "",
    "summary": "",
    "sentiment": "",
    "isOptOut": true
  },
  {
    "atomicId": "3dbf91e8-5762-495d-9d6f-730e40a1e247",
    "phoneNumber": "12088900840",
    "receivedAt": "2026-02-09T18:04:09+00:00",
    "originalMessage": "Stop",
    "atomicMessage": "Stop",
    "pollId": "019c29d4-81aa-733e-a72a-3983baf19a22",
    "clusterId": "",
    "theme": "Opt Out Request",
    "category": "",
    "summary": "",
    "sentiment": "",
    "isOptOut": true
  },
  {
    "atomicId": "64d0c0ed-22dd-4848-8334-1c0344ea4d88",
    "phoneNumber": "12084840091",
    "receivedAt": "2026-02-09T18:04:16+00:00",
    "originalMessage": "Reduce traffic on Meridian Rd. Do not allow the Buc-ees gas station to be built on Meridian Rs and traffic is already a problem. Thanks for asking!",
    "atomicMessage": "Reduce traffic on Meridian Rd.",
    "pollId": "019c29d4-81aa-733e-a72a-3983baf19a22",
    "clusterId": 2,
    "theme": "Traffic Congestion Management",
    "category": "Transportation",
    "summary": "Residents demand immediate action to reduce traffic volume and improve road safety through better infrastructure and enforcement.",
    "sentiment": "negative",
    "isOptOut": false
  },
  {
    "atomicId": "cc359e20-f0a0-45f3-acb9-d86ff96bc3e4",
    "phoneNumber": "12084840091",
    "receivedAt": "2026-02-09T18:04:16+00:00",
    "originalMessage": "Reduce traffic on Meridian Rd. Do not allow the Buc-ees gas station to be built on Meridian Rs and traffic is already a problem. Thanks for asking!",
    "atomicMessage": "Do not allow the Buc-ees gas station to be built on Meridian Rd.",
    "pollId": "019c29d4-81aa-733e-a72a-3983baf19a22",
    "clusterId": 0,
    "theme": "Infrastructure Maintenance",
    "category": "Infrastructure",
    "summary": "Residents demand immediate repairs to damaged roadways, safer cycling paths, and better management of invasive weeds on public sidewalks.",
    "sentiment": "negative",
    "isOptOut": false
  },
  {
    "atomicId": "c321c969-4e1a-466b-abb3-dc95baee08f2",
    "phoneNumber": "12084840091",
    "receivedAt": "2026-02-09T18:04:16+00:00",
    "originalMessage": "Reduce traffic on Meridian Rd. Do not allow the Buc-ees gas station to be built on Meridian Rs and traffic is already a problem. Thanks for asking!",
    "atomicMessage": "Traffic is already a problem in the local area.",
    "pollId": "019c29d4-81aa-733e-a72a-3983baf19a22",
    "clusterId": 2,
    "theme": "Traffic Congestion Management",
    "category": "Transportation",
    "summary": "Residents demand immediate action to reduce traffic volume and improve road safety through better infrastructure and enforcement.",
    "sentiment": "negative",
    "isOptOut": false
  },
  {
    "atomicId": "aaecc526-158d-4045-ac4f-d795426af0c8",
    "phoneNumber": "12086082423",
    "receivedAt": "2026-02-09T18:06:21+00:00",
    "originalMessage": "Limit controlled burns in residential areas. Keep illegals and Californians from voting they seem to both be just as bad. Stop building. We are getting bombarded with apartment complexed and businesses have destroyed our small town. Stop destroying the reasons we live here. ",
    "atomicMessage": "Limit controlled burns in residential areas.",
    "pollId": "019c29d4-81aa-733e-a72a-3983baf19a22",
    "clusterId": 11,
    "theme": "Public Land Management",
    "category": "Environment",
    "summary": "Residents demand an end to public land sales and stricter limits on controlled burns near residential neighborhoods.",
    "sentiment": "concerned",
    "isOptOut": false
  },
  {
    "atomicId": "d4372898-4d1b-419f-ad28-2ff943cafa5a",
    "phoneNumber": "12086082423",
    "receivedAt": "2026-02-09T18:06:21+00:00",
    "originalMessage": "Limit controlled burns in residential areas. Keep illegals and Californians from voting they seem to both be just as bad. Stop building. We are getting bombarded with apartment complexed and businesses have destroyed our small town. Stop destroying the reasons we live here. ",
    "atomicMessage": "Implement stricter voter eligibility controls.",
    "pollId": "019c29d4-81aa-733e-a72a-3983baf19a22",
    "clusterId": 3,
    "theme": "Law Enforcement Enforcement",
    "category": "Public Safety",
    "summary": "Constituents demand strict legal consequences for civil unrest and illegal immigration while rejecting local cooperation with federal immigration agencies.",
    "sentiment": "concerned",
    "isOptOut": false
  },
  {
    "atomicId": "0cb00a54-3ca0-4046-867e-9cdbd98acf4d",
    "phoneNumber": "12086082423",
    "receivedAt": "2026-02-09T18:06:21+00:00",
    "originalMessage": "Limit controlled burns in residential areas. Keep illegals and Californians from voting they seem to both be just as bad. Stop building. We are getting bombarded with apartment complexed and businesses have destroyed our small town. Stop destroying the reasons we live here. ",
    "atomicMessage": "Halt new construction projects to prevent overdevelopment.",
    "pollId": "019c29d4-81aa-733e-a72a-3983baf19a22",
    "clusterId": 4,
    "theme": "Rapid Urban Overdevelopment",
    "category": "Housing",
    "summary": "Residents demand a halt to high-density construction to protect community character and prevent strain on public infrastructure.",
    "sentiment": "concerned",
    "isOptOut": false
  },
  {
    "atomicId": "2f135f5e-99c3-4298-881d-6a2c30b3d62c",
    "phoneNumber": "12086082423",
    "receivedAt": "2026-02-09T18:06:21+00:00",
    "originalMessage": "Limit controlled burns in residential areas. Keep illegals and Californians from voting they seem to both be just as bad. Stop building. We are getting bombarded with apartment complexed and businesses have destroyed our small town. Stop destroying the reasons we live here. ",
    "atomicMessage": "Address the proliferation of apartment complexes and the impact of commercial development on the local area.",
    "pollId": "019c29d4-81aa-733e-a72a-3983baf19a22",
    "clusterId": 4,
    "theme": "Rapid Urban Overdevelopment",
    "category": "Housing",
    "summary": "Residents demand a halt to high-density construction to protect community character and prevent strain on public infrastructure.",
    "sentiment": "concerned",
    "isOptOut": false
  },
  {
    "atomicId": "8773618e-3c37-41ba-b1fa-5f21ce7be775",
    "phoneNumber": "12086082423",
    "receivedAt": "2026-02-09T18:06:21+00:00",
    "originalMessage": "Limit controlled burns in residential areas. Keep illegals and Californians from voting they seem to both be just as bad. Stop building. We are getting bombarded with apartment complexed and businesses have destroyed our small town. Stop destroying the reasons we live here. ",
    "atomicMessage": "Preserve the character and quality of life in this community.",
    "pollId": "019c29d4-81aa-733e-a72a-3983baf19a22",
    "clusterId": 4,
    "theme": "Rapid Urban Overdevelopment",
    "category": "Housing",
    "summary": "Residents demand a halt to high-density construction to protect community character and prevent strain on public infrastructure.",
    "sentiment": "concerned",
    "isOptOut": false
  },
  {
    "atomicId": "845036e5-0413-4aa1-9dba-3695cde45a04",
    "phoneNumber": "12087093692",
    "receivedAt": "2026-02-09T18:07:32+00:00",
    "originalMessage": "Stop",
    "atomicMessage": "Stop",
    "pollId": "019c29d4-81aa-733e-a72a-3983baf19a22",
    "clusterId": "",
    "theme": "Opt Out Request",
    "category": "",
    "summary": "",
    "sentiment": "",
    "isOptOut": true
  },
  {
    "atomicId": "d4284dcf-cf69-4ec6-9834-67a66de0b920",
    "phoneNumber": "17023719993",
    "receivedAt": "2026-02-09T18:09:14+00:00",
    "originalMessage": "Stop",
    "atomicMessage": "Stop",
    "pollId": "019c29d4-81aa-733e-a72a-3983baf19a22",
    "clusterId": "",
    "theme": "Opt Out Request",
    "category": "",
    "summary": "",
    "sentiment": "",
    "isOptOut": true
  },
  {
    "atomicId": "026535e1-72f9-4829-b660-b7920016875c",
    "phoneNumber": "12086312063",
    "receivedAt": "2026-02-09T18:14:38+00:00",
    "originalMessage": "STOP",
    "atomicMessage": "STOP",
    "pollId": "019c29d4-81aa-733e-a72a-3983baf19a22",
    "clusterId": "",
    "theme": "Opt Out Request",
    "category": "",
    "summary": "",
    "sentiment": "",
    "isOptOut": true
  },
  {
    "atomicId": "879cb9b6-a7e6-4eec-9752-f865146a8cdd",
    "phoneNumber": "12086028563",
    "receivedAt": "2026-02-09T18:17:46+00:00",
    "originalMessage": "STOP",
    "atomicMessage": "STOP",
    "pollId": "019c29d4-81aa-733e-a72a-3983baf19a22",
    "clusterId": "",
    "theme": "Opt Out Request",
    "category": "",
    "summary": "",
    "sentiment": "",
    "isOptOut": true
  },
  {
    "atomicId": "7539c88c-d1a2-4ec7-a0e5-ffc0c6732cd0",
    "phoneNumber": "12087948846",
    "receivedAt": "2026-02-09T18:19:08+00:00",
    "originalMessage": "STOP",
    "atomicMessage": "STOP",
    "pollId": "019c29d4-81aa-733e-a72a-3983baf19a22",
    "clusterId": "",
    "theme": "Opt Out Request",
    "category": "",
    "summary": "",
    "sentiment": "",
    "isOptOut": true
  },
  {
    "atomicId": "a3c436c0-06a5-49e1-a3c5-7ffe581c5128",
    "phoneNumber": "12083537197",
    "receivedAt": "2026-02-09T18:21:44+00:00",
    "originalMessage": "The stopping of all public land sales. ",
    "atomicMessage": "The stopping of all public land sales.",
    "pollId": "019c29d4-81aa-733e-a72a-3983baf19a22",
    "clusterId": 11,
    "theme": "Public Land Management",
    "category": "Environment",
    "summary": "Residents demand an end to public land sales and stricter limits on controlled burns near residential neighborhoods.",
    "sentiment": "concerned",
    "isOptOut": false
  },
  {
    "atomicId": "de6e75f8-9804-4200-abfa-5197e41996af",
    "phoneNumber": "12088502185",
    "receivedAt": "2026-02-09T18:29:37+00:00",
    "originalMessage": "I dont want ICE in our community. I dont want our schools to have armed men patrolling the school grounds. I want affordable housing. ",
    "atomicMessage": "I do not want immigration enforcement agencies in this community.",
    "pollId": "019c29d4-81aa-733e-a72a-3983baf19a22",
    "clusterId": 3,
    "theme": "Law Enforcement Enforcement",
    "category": "Public Safety",
    "summary": "Constituents demand strict legal consequences for civil unrest and illegal immigration while rejecting local cooperation with federal immigration agencies.",
    "sentiment": "concerned",
    "isOptOut": false
  },
  {
    "atomicId": "9a924cc9-c66f-45fc-a292-91020d9ba12f",
    "phoneNumber": "12088502185",
    "receivedAt": "2026-02-09T18:29:37+00:00",
    "originalMessage": "I dont want ICE in our community. I dont want our schools to have armed men patrolling the school grounds. I want affordable housing. ",
    "atomicMessage": "I do not want local schools to have armed personnel patrolling the school grounds.",
    "pollId": "019c29d4-81aa-733e-a72a-3983baf19a22",
    "clusterId": 1,
    "theme": "School Safety Measures",
    "category": "Education",
    "summary": "Constituents disagree on whether to deploy armed personnel within local schools to prevent violence.",
    "sentiment": "mixed",
    "isOptOut": false
  },
  {
    "atomicId": "dca74e75-2222-42f6-bf20-cc3d9d13daec",
    "phoneNumber": "12088502185",
    "receivedAt": "2026-02-09T18:29:37+00:00",
    "originalMessage": "I dont want ICE in our community. I dont want our schools to have armed men patrolling the school grounds. I want affordable housing. ",
    "atomicMessage": "I want affordable housing in the local area.",
    "pollId": "019c29d4-81aa-733e-a72a-3983baf19a22",
    "clusterId": 6,
    "theme": "Affordable Housing Expansion",
    "category": "Housing",
    "summary": "Residents demand lower housing costs and rent protections to combat displacement caused by new population growth.",
    "sentiment": "concerned",
    "isOptOut": false
  },
  {
    "atomicId": "6e9efd04-7574-41b2-a94c-42a00059b0f9",
    "phoneNumber": "19074409779",
    "receivedAt": "2026-02-09T18:27:53+00:00",
    "originalMessage": "Stop",
    "atomicMessage": "Stop",
    "pollId": "019c29d4-81aa-733e-a72a-3983baf19a22",
    "clusterId": "",
    "theme": "Opt Out Request",
    "category": "",
    "summary": "",
    "sentiment": "",
    "isOptOut": true
  },
  {
    "atomicId": "5f1486f0-1fd5-439e-ae05-573920f59036",
    "phoneNumber": "12088502185",
    "receivedAt": "2026-02-09T18:29:37+00:00",
    "originalMessage": "Im a born and raised native. I dont flaunt that as a status symbol, but it gives me the right to exist here without fear of poverty and violence. This town has changed a lot in my 31 years and a lot has been good. There are going to be growing pains, but theyre adding up to be a problem on their own. ",
    "atomicMessage": "The local area is experiencing significant issues with poverty and economic instability.",
    "pollId": "019c29d4-81aa-733e-a72a-3983baf19a22",
    "clusterId": 0,
    "theme": "Infrastructure Maintenance",
    "category": "Infrastructure",
    "summary": "Residents demand immediate repairs to damaged roadways, safer cycling paths, and better management of invasive weeds on public sidewalks.",
    "sentiment": "negative",
    "isOptOut": false
  },
  {
    "atomicId": "d58f7e7d-971f-40d1-863a-5a29b1d6feab",
    "phoneNumber": "12088502185",
    "receivedAt": "2026-02-09T18:29:37+00:00",
    "originalMessage": "Im a born and raised native. I dont flaunt that as a status symbol, but it gives me the right to exist here without fear of poverty and violence. This town has changed a lot in my 31 years and a lot has been good. There are going to be growing pains, but theyre adding up to be a problem on their own. ",
    "atomicMessage": "The community is facing increasing concerns regarding public safety and violence.",
    "pollId": "019c29d4-81aa-733e-a72a-3983baf19a22",
    "clusterId": 8,
    "theme": "Community Safety Enhancements",
    "category": "Community Services",
    "summary": "Residents demand a comprehensive approach to public safety that combines park development with drug prevention and violence reduction.",
    "sentiment": "concerned",
    "isOptOut": false
  },
  {
    "atomicId": "1f57ce00-7e15-4dd3-81e2-560a0b025ccc",
    "phoneNumber": "12088502185",
    "receivedAt": "2026-02-09T18:29:37+00:00",
    "originalMessage": "Im a born and raised native. I dont flaunt that as a status symbol, but it gives me the right to exist here without fear of poverty and violence. This town has changed a lot in my 31 years and a lot has been good. There are going to be growing pains, but theyre adding up to be a problem on their own. ",
    "atomicMessage": "Rapid urban growth and development in the area are creating systemic problems and growing pains.",
    "pollId": "019c29d4-81aa-733e-a72a-3983baf19a22",
    "clusterId": 4,
    "theme": "Rapid Urban Overdevelopment",
    "category": "Housing",
    "summary": "Residents demand a halt to high-density construction to protect community character and prevent strain on public infrastructure.",
    "sentiment": "concerned",
    "isOptOut": false
  },
  {
    "atomicId": "38fd9c32-9e52-4d49-af26-26199fe4c556",
    "phoneNumber": "12089417823",
    "receivedAt": "2026-02-09T18:29:45+00:00",
    "originalMessage": "Stop",
    "atomicMessage": "Stop",
    "pollId": "019c29d4-81aa-733e-a72a-3983baf19a22",
    "clusterId": "",
    "theme": "Opt Out Request",
    "category": "",
    "summary": "",
    "sentiment": "",
    "isOptOut": true
  },
  {
    "atomicId": "347e60c7-b9cb-4375-8405-37b1d4cdddbe",
    "phoneNumber": "12089072297",
    "receivedAt": "2026-02-09T18:43:31+00:00",
    "originalMessage": "Stop",
    "atomicMessage": "Stop",
    "pollId": "019c29d4-81aa-733e-a72a-3983baf19a22",
    "clusterId": "",
    "theme": "Opt Out Request",
    "category": "",
    "summary": "",
    "sentiment": "",
    "isOptOut": true
  },
  {
    "atomicId": "24e9a4c9-ce6a-47b1-ac6a-f52b69f2616e",
    "phoneNumber": "12083150805",
    "receivedAt": "2026-02-09T18:44:03+00:00",
    "originalMessage": "Rent cap. ",
    "atomicMessage": "The implementation of a rent cap to address housing affordability and tenant protections.",
    "pollId": "019c29d4-81aa-733e-a72a-3983baf19a22",
    "clusterId": 6,
    "theme": "Affordable Housing Expansion",
    "category": "Housing",
    "summary": "Residents demand lower housing costs and rent protections to combat displacement caused by new population growth.",
    "sentiment": "concerned",
    "isOptOut": false
  },
  {
    "atomicId": "c12804d1-0c63-400b-9cf3-ef46dc5bbf87",
    "phoneNumber": "12087942296",
    "receivedAt": "2026-02-09T18:45:35+00:00",
    "originalMessage": "Medicaid services (behavioral / community based resources and dental) being cut, and the parental choice tax credit ",
    "atomicMessage": "Medicaid services including behavioral community based resources and dental care are being cut",
    "pollId": "019c29d4-81aa-733e-a72a-3983baf19a22",
    "clusterId": 1,
    "theme": "School Safety Measures",
    "category": "Education",
    "summary": "Constituents disagree on whether to deploy armed personnel within local schools to prevent violence.",
    "sentiment": "mixed",
    "isOptOut": false
  },
  {
    "atomicId": "82e8cdeb-7773-4d4e-843c-31fe94876813",
    "phoneNumber": "12087942296",
    "receivedAt": "2026-02-09T18:45:35+00:00",
    "originalMessage": "Medicaid services (behavioral / community based resources and dental) being cut, and the parental choice tax credit ",
    "atomicMessage": "The parental choice tax credit",
    "pollId": "019c29d4-81aa-733e-a72a-3983baf19a22",
    "clusterId": 1,
    "theme": "School Safety Measures",
    "category": "Education",
    "summary": "Constituents disagree on whether to deploy armed personnel within local schools to prevent violence.",
    "sentiment": "mixed",
    "isOptOut": false
  },
  {
    "atomicId": "a6c2ec6e-fef1-44d1-9bf6-dbfb3c048b67",
    "phoneNumber": "12087567109",
    "receivedAt": "2026-02-09T18:46:19+00:00",
    "originalMessage": "Find a solution to the morning traffic jam from Meridian Road to Eagle. ",
    "atomicMessage": "Find a solution to the morning traffic jam from Meridian Road to the local area.",
    "pollId": "019c29d4-81aa-733e-a72a-3983baf19a22",
    "clusterId": 2,
    "theme": "Traffic Congestion Management",
    "category": "Transportation",
    "summary": "Residents demand immediate action to reduce traffic volume and improve road safety through better infrastructure and enforcement.",
    "sentiment": "negative",
    "isOptOut": false
  },
  {
    "atomicId": "17badf83-d2c9-4775-b475-9feaf8435f50",
    "phoneNumber": "12088708494",
    "receivedAt": "2026-02-09T18:59:05+00:00",
    "originalMessage": "STOP",
    "atomicMessage": "STOP",
    "pollId": "019c29d4-81aa-733e-a72a-3983baf19a22",
    "clusterId": "",
    "theme": "Opt Out Request",
    "category": "",
    "summary": "",
    "sentiment": "",
    "isOptOut": true
  },
  {
    "atomicId": "6da5ca1b-09a1-46c4-a5ef-ffd7a98c7823",
    "phoneNumber": "12088718130",
    "receivedAt": "2026-02-09T18:59:52+00:00",
    "originalMessage": "While not specifically Meridian, I love that West Ada schools are exploring options for armed security guards.  I'm a high-level firearms instructor with some specialized knowledge in this area.  Leaving the handling of an active threat up to the 911 system and waiting through the entire response sequence pretty much guarantees a huge win (i.e., international notoriety) for the attacker and an unforgettable tragedy for our community.  Get capable, armed people (I would add certain concealed carriers, too) in there on every hallway, on every playground, and in every common area!  And I say that as a parent of a 7th-grader in the WA school district.\n\nAfter that, we must NEVER emulate Minneapolis!  If we don't like a law, people in a constitutional republic must communicate with their elected representatives about changing the law.  Impeding law enforcement, urban occupations that destroy businesses, rioting, looting, burning, and ANY physical violence MUST be met with the full power of law enforcement--including a prosecuting attorney and judges who will make examples of the rioters.\n\nOn a lighter note, can something be done about the sprawling goat-head thorn vines on some of our sidewalks?  (Locust Grove, just north of Franklin, for example.)  That's bad news for kids on bikes and even a real nuisance in shoes and car tires.",
    "atomicMessage": "Local schools should explore options for armed security guards and capable armed personnel in hallways and common areas to prevent tragedies.",
    "pollId": "019c29d4-81aa-733e-a72a-3983baf19a22",
    "clusterId": 1,
    "theme": "School Safety Measures",
    "category": "Education",
    "summary": "Constituents disagree on whether to deploy armed personnel within local schools to prevent violence.",
    "sentiment": "mixed",
    "isOptOut": false
  },
  {
    "atomicId": "4704cbbf-8452-41bb-956e-8eaab2044b83",
    "phoneNumber": "12088718130",
    "receivedAt": "2026-02-09T18:59:52+00:00",
    "originalMessage": "While not specifically Meridian, I love that West Ada schools are exploring options for armed security guards.  I'm a high-level firearms instructor with some specialized knowledge in this area.  Leaving the handling of an active threat up to the 911 system and waiting through the entire response sequence pretty much guarantees a huge win (i.e., international notoriety) for the attacker and an unforgettable tragedy for our community.  Get capable, armed people (I would add certain concealed carriers, too) in there on every hallway, on every playground, and in every common area!  And I say that as a parent of a 7th-grader in the WA school district.\n\nAfter that, we must NEVER emulate Minneapolis!  If we don't like a law, people in a constitutional republic must communicate with their elected representatives about changing the law.  Impeding law enforcement, urban occupations that destroy businesses, rioting, looting, burning, and ANY physical violence MUST be met with the full power of law enforcement--including a prosecuting attorney and judges who will make examples of the rioters.\n\nOn a lighter note, can something be done about the sprawling goat-head thorn vines on some of our sidewalks?  (Locust Grove, just north of Franklin, for example.)  That's bad news for kids on bikes and even a real nuisance in shoes and car tires.",
    "atomicMessage": "The local school district should consider allowing certain concealed carriers to provide security on playgrounds and school grounds.",
    "pollId": "019c29d4-81aa-733e-a72a-3983baf19a22",
    "clusterId": 1,
    "theme": "School Safety Measures",
    "category": "Education",
    "summary": "Constituents disagree on whether to deploy armed personnel within local schools to prevent violence.",
    "sentiment": "mixed",
    "isOptOut": false
  },
  {
    "atomicId": "22c0c891-2e01-473d-95b1-4238217f626b",
    "phoneNumber": "12088718130",
    "receivedAt": "2026-02-09T18:59:52+00:00",
    "originalMessage": "While not specifically Meridian, I love that West Ada schools are exploring options for armed security guards.  I'm a high-level firearms instructor with some specialized knowledge in this area.  Leaving the handling of an active threat up to the 911 system and waiting through the entire response sequence pretty much guarantees a huge win (i.e., international notoriety) for the attacker and an unforgettable tragedy for our community.  Get capable, armed people (I would add certain concealed carriers, too) in there on every hallway, on every playground, and in every common area!  And I say that as a parent of a 7th-grader in the WA school district.\n\nAfter that, we must NEVER emulate Minneapolis!  If we don't like a law, people in a constitutional republic must communicate with their elected representatives about changing the law.  Impeding law enforcement, urban occupations that destroy businesses, rioting, looting, burning, and ANY physical violence MUST be met with the full power of law enforcement--including a prosecuting attorney and judges who will make examples of the rioters.\n\nOn a lighter note, can something be done about the sprawling goat-head thorn vines on some of our sidewalks?  (Locust Grove, just north of Franklin, for example.)  That's bad news for kids on bikes and even a real nuisance in shoes and car tires.",
    "atomicMessage": "Citizens must communicate with elected representatives to change laws rather than engaging in urban occupations, rioting, or looting.",
    "pollId": "019c29d4-81aa-733e-a72a-3983baf19a22",
    "clusterId": 3,
    "theme": "Law Enforcement Enforcement",
    "category": "Public Safety",
    "summary": "Constituents demand strict legal consequences for civil unrest and illegal immigration while rejecting local cooperation with federal immigration agencies.",
    "sentiment": "concerned",
    "isOptOut": false
  },
  {
    "atomicId": "b0e1e26f-0e64-401a-866b-87a9ed205279",
    "phoneNumber": "12088718130",
    "receivedAt": "2026-02-09T18:59:52+00:00",
    "originalMessage": "While not specifically Meridian, I love that West Ada schools are exploring options for armed security guards.  I'm a high-level firearms instructor with some specialized knowledge in this area.  Leaving the handling of an active threat up to the 911 system and waiting through the entire response sequence pretty much guarantees a huge win (i.e., international notoriety) for the attacker and an unforgettable tragedy for our community.  Get capable, armed people (I would add certain concealed carriers, too) in there on every hallway, on every playground, and in every common area!  And I say that as a parent of a 7th-grader in the WA school district.\n\nAfter that, we must NEVER emulate Minneapolis!  If we don't like a law, people in a constitutional republic must communicate with their elected representatives about changing the law.  Impeding law enforcement, urban occupations that destroy businesses, rioting, looting, burning, and ANY physical violence MUST be met with the full power of law enforcement--including a prosecuting attorney and judges who will make examples of the rioters.\n\nOn a lighter note, can something be done about the sprawling goat-head thorn vines on some of our sidewalks?  (Locust Grove, just north of Franklin, for example.)  That's bad news for kids on bikes and even a real nuisance in shoes and car tires.",
    "atomicMessage": "Law enforcement and the justice system must use full legal power to prosecute physical violence and property destruction during civil unrest.",
    "pollId": "019c29d4-81aa-733e-a72a-3983baf19a22",
    "clusterId": 3,
    "theme": "Law Enforcement Enforcement",
    "category": "Public Safety",
    "summary": "Constituents demand strict legal consequences for civil unrest and illegal immigration while rejecting local cooperation with federal immigration agencies.",
    "sentiment": "concerned",
    "isOptOut": false
  },
  {
    "atomicId": "2e135db4-3f14-40ac-a597-45f273ca4c87",
    "phoneNumber": "12088718130",
    "receivedAt": "2026-02-09T18:59:52+00:00",
    "originalMessage": "While not specifically Meridian, I love that West Ada schools are exploring options for armed security guards.  I'm a high-level firearms instructor with some specialized knowledge in this area.  Leaving the handling of an active threat up to the 911 system and waiting through the entire response sequence pretty much guarantees a huge win (i.e., international notoriety) for the attacker and an unforgettable tragedy for our community.  Get capable, armed people (I would add certain concealed carriers, too) in there on every hallway, on every playground, and in every common area!  And I say that as a parent of a 7th-grader in the WA school district.\n\nAfter that, we must NEVER emulate Minneapolis!  If we don't like a law, people in a constitutional republic must communicate with their elected representatives about changing the law.  Impeding law enforcement, urban occupations that destroy businesses, rioting, looting, burning, and ANY physical violence MUST be met with the full power of law enforcement--including a prosecuting attorney and judges who will make examples of the rioters.\n\nOn a lighter note, can something be done about the sprawling goat-head thorn vines on some of our sidewalks?  (Locust Grove, just north of Franklin, for example.)  That's bad news for kids on bikes and even a real nuisance in shoes and car tires.",
    "atomicMessage": "The local area needs to address the sprawling goat-head thorn vines on sidewalks, specifically on Locust Grove north of Franklin, as they damage bike tires and shoes.",
    "pollId": "019c29d4-81aa-733e-a72a-3983baf19a22",
    "clusterId": 0,
    "theme": "Infrastructure Maintenance",
    "category": "Infrastructure",
    "summary": "Residents demand immediate repairs to damaged roadways, safer cycling paths, and better management of invasive weeds on public sidewalks.",
    "sentiment": "negative",
    "isOptOut": false
  },
  {
    "atomicId": "5c9d7641-86e8-432e-9636-b47d02784a13",
    "phoneNumber": "12084846682",
    "receivedAt": "2026-02-09T19:00:23+00:00",
    "originalMessage": "Stop",
    "atomicMessage": "Stop",
    "pollId": "019c29d4-81aa-733e-a72a-3983baf19a22",
    "clusterId": "",
    "theme": "Opt Out Request",
    "category": "",
    "summary": "",
    "sentiment": "",
    "isOptOut": true
  },
  {
    "atomicId": "b9eeeaeb-a9a7-4e4e-b1e0-6cff8178c1d8",
    "phoneNumber": "12089396290",
    "receivedAt": "2026-02-09T19:07:55+00:00",
    "originalMessage": "STOP",
    "atomicMessage": "STOP",
    "pollId": "019c29d4-81aa-733e-a72a-3983baf19a22",
    "clusterId": "",
    "theme": "Opt Out Request",
    "category": "",
    "summary": "",
    "sentiment": "",
    "isOptOut": true
  },
  {
    "atomicId": "cc42e239-3977-4b33-aea3-684c383a8eec",
    "phoneNumber": "12087319793",
    "receivedAt": "2026-02-09T19:11:28+00:00",
    "originalMessage": "Stop",
    "atomicMessage": "Stop",
    "pollId": "019c29d4-81aa-733e-a72a-3983baf19a22",
    "clusterId": "",
    "theme": "Opt Out Request",
    "category": "",
    "summary": "",
    "sentiment": "",
    "isOptOut": true
  },
  {
    "atomicId": "fede9d24-bd24-4cb9-9827-8deb6b5bf433",
    "phoneNumber": "19495420381",
    "receivedAt": "2026-02-09T19:41:55+00:00",
    "originalMessage": "Last year there was a top coating on Meridian road at the overpass of the freeway. The slur looked nice, but the pot holes were left there. It is frustrating to have to drive around them.",
    "atomicMessage": "There was a top coating on Meridian road at the overpass of the freeway where the slurry looked nice but the pot holes were left untreated and require repair.",
    "pollId": "019c29d4-81aa-733e-a72a-3983baf19a22",
    "clusterId": 0,
    "theme": "Infrastructure Maintenance",
    "category": "Infrastructure",
    "summary": "Residents demand immediate repairs to damaged roadways, safer cycling paths, and better management of invasive weeds on public sidewalks.",
    "sentiment": "negative",
    "isOptOut": false
  },
  {
    "atomicId": "cd91bd5a-76a3-4dc1-a832-a36517f92239",
    "phoneNumber": "12088669274",
    "receivedAt": "2026-02-09T19:47:04+00:00",
    "originalMessage": "Traffic patterns, over building apartments without available parking ",
    "atomicMessage": "Traffic patterns in the local area",
    "pollId": "019c29d4-81aa-733e-a72a-3983baf19a22",
    "clusterId": 2,
    "theme": "Traffic Congestion Management",
    "category": "Transportation",
    "summary": "Residents demand immediate action to reduce traffic volume and improve road safety through better infrastructure and enforcement.",
    "sentiment": "negative",
    "isOptOut": false
  },
  {
    "atomicId": "a447c768-4cb4-44ca-8dae-3267598e40c7",
    "phoneNumber": "12088669274",
    "receivedAt": "2026-02-09T19:47:04+00:00",
    "originalMessage": "Traffic patterns, over building apartments without available parking ",
    "atomicMessage": "Over building apartments without available parking in the local area",
    "pollId": "019c29d4-81aa-733e-a72a-3983baf19a22",
    "clusterId": 2,
    "theme": "Traffic Congestion Management",
    "category": "Transportation",
    "summary": "Residents demand immediate action to reduce traffic volume and improve road safety through better infrastructure and enforcement.",
    "sentiment": "negative",
    "isOptOut": false
  },
  {
    "atomicId": "22d89a51-c0ba-400e-8c99-bc5f568912fa",
    "phoneNumber": "15597768953",
    "receivedAt": "2026-02-09T20:05:30+00:00",
    "originalMessage": "The massive construction increase in our district of multifamily homes. The impact to roads, schools, and public services. \nIn the last 2 years we've seen such an impact. And the huge project at Ten Mile to Black Cat. Why does Meridian need another Village.\nAnd the industrial buildings that have been built and sit empty. Why are we destroying our beautiful farmlands for empty, ugly buildings. Our neighborhoods have changed so drastically they are not recognizable from 5 years ago.",
    "atomicMessage": "The massive increase in construction of multifamily homes in the local area.",
    "pollId": "019c29d4-81aa-733e-a72a-3983baf19a22",
    "clusterId": 4,
    "theme": "Rapid Urban Overdevelopment",
    "category": "Housing",
    "summary": "Residents demand a halt to high-density construction to protect community character and prevent strain on public infrastructure.",
    "sentiment": "concerned",
    "isOptOut": false
  },
  {
    "atomicId": "8cbbe56d-3ca0-40ac-ba16-337c5e26a590",
    "phoneNumber": "15597768953",
    "receivedAt": "2026-02-09T20:05:30+00:00",
    "originalMessage": "The massive construction increase in our district of multifamily homes. The impact to roads, schools, and public services. \nIn the last 2 years we've seen such an impact. And the huge project at Ten Mile to Black Cat. Why does Meridian need another Village.\nAnd the industrial buildings that have been built and sit empty. Why are we destroying our beautiful farmlands for empty, ugly buildings. Our neighborhoods have changed so drastically they are not recognizable from 5 years ago.",
    "atomicMessage": "The impact of development on roads, schools, and public services.",
    "pollId": "019c29d4-81aa-733e-a72a-3983baf19a22",
    "clusterId": 4,
    "theme": "Rapid Urban Overdevelopment",
    "category": "Housing",
    "summary": "Residents demand a halt to high-density construction to protect community character and prevent strain on public infrastructure.",
    "sentiment": "concerned",
    "isOptOut": false
  },
  {
    "atomicId": "ae3e384a-148c-4e4b-be8d-16c1ba32c00f",
    "phoneNumber": "15597768953",
    "receivedAt": "2026-02-09T20:05:30+00:00",
    "originalMessage": "The massive construction increase in our district of multifamily homes. The impact to roads, schools, and public services. \nIn the last 2 years we've seen such an impact. And the huge project at Ten Mile to Black Cat. Why does Meridian need another Village.\nAnd the industrial buildings that have been built and sit empty. Why are we destroying our beautiful farmlands for empty, ugly buildings. Our neighborhoods have changed so drastically they are not recognizable from 5 years ago.",
    "atomicMessage": "Concerns regarding the large-scale development project between Ten Mile and Black Cat.",
    "pollId": "019c29d4-81aa-733e-a72a-3983baf19a22",
    "clusterId": 4,
    "theme": "Rapid Urban Overdevelopment",
    "category": "Housing",
    "summary": "Residents demand a halt to high-density construction to protect community character and prevent strain on public infrastructure.",
    "sentiment": "concerned",
    "isOptOut": false
  },
  {
    "atomicId": "6e85e300-59f8-4bc0-ab2a-3ba39f1e3c0d",
    "phoneNumber": "15597768953",
    "receivedAt": "2026-02-09T20:05:30+00:00",
    "originalMessage": "The massive construction increase in our district of multifamily homes. The impact to roads, schools, and public services. \nIn the last 2 years we've seen such an impact. And the huge project at Ten Mile to Black Cat. Why does Meridian need another Village.\nAnd the industrial buildings that have been built and sit empty. Why are we destroying our beautiful farmlands for empty, ugly buildings. Our neighborhoods have changed so drastically they are not recognizable from 5 years ago.",
    "atomicMessage": "The development of industrial buildings that remain vacant and the loss of local farmlands.",
    "pollId": "019c29d4-81aa-733e-a72a-3983baf19a22",
    "clusterId": 4,
    "theme": "Rapid Urban Overdevelopment",
    "category": "Housing",
    "summary": "Residents demand a halt to high-density construction to protect community character and prevent strain on public infrastructure.",
    "sentiment": "concerned",
    "isOptOut": false
  },
  {
    "atomicId": "a6f89b3e-4c88-4078-95b1-829e2fbac944",
    "phoneNumber": "15597768953",
    "receivedAt": "2026-02-09T20:05:30+00:00",
    "originalMessage": "The massive construction increase in our district of multifamily homes. The impact to roads, schools, and public services. \nIn the last 2 years we've seen such an impact. And the huge project at Ten Mile to Black Cat. Why does Meridian need another Village.\nAnd the industrial buildings that have been built and sit empty. Why are we destroying our beautiful farmlands for empty, ugly buildings. Our neighborhoods have changed so drastically they are not recognizable from 5 years ago.",
    "atomicMessage": "The drastic change in neighborhood character and the loss of community identity over the last five years.",
    "pollId": "019c29d4-81aa-733e-a72a-3983baf19a22",
    "clusterId": 4,
    "theme": "Rapid Urban Overdevelopment",
    "category": "Housing",
    "summary": "Residents demand a halt to high-density construction to protect community character and prevent strain on public infrastructure.",
    "sentiment": "concerned",
    "isOptOut": false
  },
  {
    "atomicId": "0d312bc0-bcb0-4184-995a-d65518ebda21",
    "phoneNumber": "15592849710",
    "receivedAt": "2026-02-09T20:12:36+00:00",
    "originalMessage": "1. Deport ALL illegals in the state 2. Crime - tougher sentencing. 3. Eliminate homeless. 4. Less housing density - bigger lots and more green space & less new subdivisions. 5. Work with downtown Meridian to bring in/support more small businesses - locally owned restaurants, shops, florists, etc. 6. Traffic - increase infrastructure. ",
    "atomicMessage": "Deport all undocumented individuals in the state.",
    "pollId": "019c29d4-81aa-733e-a72a-3983baf19a22",
    "clusterId": 3,
    "theme": "Law Enforcement Enforcement",
    "category": "Public Safety",
    "summary": "Constituents demand strict legal consequences for civil unrest and illegal immigration while rejecting local cooperation with federal immigration agencies.",
    "sentiment": "concerned",
    "isOptOut": false
  },
  {
    "atomicId": "a2c14659-b9d6-4cb5-b5d0-20aa901aa451",
    "phoneNumber": "15592849710",
    "receivedAt": "2026-02-09T20:12:36+00:00",
    "originalMessage": "1. Deport ALL illegals in the state 2. Crime - tougher sentencing. 3. Eliminate homeless. 4. Less housing density - bigger lots and more green space & less new subdivisions. 5. Work with downtown Meridian to bring in/support more small businesses - locally owned restaurants, shops, florists, etc. 6. Traffic - increase infrastructure. ",
    "atomicMessage": "Implement tougher sentencing to address crime.",
    "pollId": "019c29d4-81aa-733e-a72a-3983baf19a22",
    "clusterId": 3,
    "theme": "Law Enforcement Enforcement",
    "category": "Public Safety",
    "summary": "Constituents demand strict legal consequences for civil unrest and illegal immigration while rejecting local cooperation with federal immigration agencies.",
    "sentiment": "concerned",
    "isOptOut": false
  },
  {
    "atomicId": "c66ddf18-ae08-4457-8c19-eeac5fdfaa8b",
    "phoneNumber": "15592849710",
    "receivedAt": "2026-02-09T20:12:36+00:00",
    "originalMessage": "1. Deport ALL illegals in the state 2. Crime - tougher sentencing. 3. Eliminate homeless. 4. Less housing density - bigger lots and more green space & less new subdivisions. 5. Work with downtown Meridian to bring in/support more small businesses - locally owned restaurants, shops, florists, etc. 6. Traffic - increase infrastructure. ",
    "atomicMessage": "Address and eliminate homelessness in the area.",
    "pollId": "019c29d4-81aa-733e-a72a-3983baf19a22",
    "clusterId": 6,
    "theme": "Affordable Housing Expansion",
    "category": "Housing",
    "summary": "Residents demand lower housing costs and rent protections to combat displacement caused by new population growth.",
    "sentiment": "concerned",
    "isOptOut": false
  },
  {
    "atomicId": "013f7c87-7912-4342-b201-b1279d70e995",
    "phoneNumber": "15592849710",
    "receivedAt": "2026-02-09T20:12:36+00:00",
    "originalMessage": "1. Deport ALL illegals in the state 2. Crime - tougher sentencing. 3. Eliminate homeless. 4. Less housing density - bigger lots and more green space & less new subdivisions. 5. Work with downtown Meridian to bring in/support more small businesses - locally owned restaurants, shops, florists, etc. 6. Traffic - increase infrastructure. ",
    "atomicMessage": "Reduce housing density by requiring larger lots and more green space while limiting new subdivisions.",
    "pollId": "019c29d4-81aa-733e-a72a-3983baf19a22",
    "clusterId": 4,
    "theme": "Rapid Urban Overdevelopment",
    "category": "Housing",
    "summary": "Residents demand a halt to high-density construction to protect community character and prevent strain on public infrastructure.",
    "sentiment": "concerned",
    "isOptOut": false
  },
  {
    "atomicId": "2ad2ee62-29ce-4e1f-be9c-d77c321704cd",
    "phoneNumber": "15592849710",
    "receivedAt": "2026-02-09T20:12:36+00:00",
    "originalMessage": "1. Deport ALL illegals in the state 2. Crime - tougher sentencing. 3. Eliminate homeless. 4. Less housing density - bigger lots and more green space & less new subdivisions. 5. Work with downtown Meridian to bring in/support more small businesses - locally owned restaurants, shops, florists, etc. 6. Traffic - increase infrastructure. ",
    "atomicMessage": "Work with the downtown area to support more small businesses including locally owned restaurants, shops, and florists.",
    "pollId": "019c29d4-81aa-733e-a72a-3983baf19a22",
    "clusterId": 6,
    "theme": "Affordable Housing Expansion",
    "category": "Housing",
    "summary": "Residents demand lower housing costs and rent protections to combat displacement caused by new population growth.",
    "sentiment": "concerned",
    "isOptOut": false
  },
  {
    "atomicId": "9931cd96-b7a6-4596-b3c7-463ed95f3608",
    "phoneNumber": "15592849710",
    "receivedAt": "2026-02-09T20:12:36+00:00",
    "originalMessage": "1. Deport ALL illegals in the state 2. Crime - tougher sentencing. 3. Eliminate homeless. 4. Less housing density - bigger lots and more green space & less new subdivisions. 5. Work with downtown Meridian to bring in/support more small businesses - locally owned restaurants, shops, florists, etc. 6. Traffic - increase infrastructure. ",
    "atomicMessage": "Increase infrastructure to address traffic concerns.",
    "pollId": "019c29d4-81aa-733e-a72a-3983baf19a22",
    "clusterId": 2,
    "theme": "Traffic Congestion Management",
    "category": "Transportation",
    "summary": "Residents demand immediate action to reduce traffic volume and improve road safety through better infrastructure and enforcement.",
    "sentiment": "negative",
    "isOptOut": false
  },
  {
    "atomicId": "04e8e782-5b03-4810-b9c4-4d8e4ce9ae73",
    "phoneNumber": "12089959928",
    "receivedAt": "2026-02-09T20:25:03+00:00",
    "originalMessage": "STOP",
    "atomicMessage": "STOP",
    "pollId": "019c29d4-81aa-733e-a72a-3983baf19a22",
    "clusterId": "",
    "theme": "Opt Out Request",
    "category": "",
    "summary": "",
    "sentiment": "",
    "isOptOut": true
  },
  {
    "atomicId": "f2447586-9c44-43bd-9a92-3f6b1b278aba",
    "phoneNumber": "19073513615",
    "receivedAt": "2026-02-09T20:25:26+00:00",
    "originalMessage": "Stop",
    "atomicMessage": "Stop",
    "pollId": "019c29d4-81aa-733e-a72a-3983baf19a22",
    "clusterId": "",
    "theme": "Opt Out Request",
    "category": "",
    "summary": "",
    "sentiment": "",
    "isOptOut": true
  },
  {
    "atomicId": "90255c0c-3f92-4b12-b141-f040aa5b6b40",
    "phoneNumber": "16024187014",
    "receivedAt": "2026-02-09T20:35:09+00:00",
    "originalMessage": "Concern with rapid growth and unaffordable housing ",
    "atomicMessage": "Concern with rapid growth in the local area",
    "pollId": "019c29d4-81aa-733e-a72a-3983baf19a22",
    "clusterId": 4,
    "theme": "Rapid Urban Overdevelopment",
    "category": "Housing",
    "summary": "Residents demand a halt to high-density construction to protect community character and prevent strain on public infrastructure.",
    "sentiment": "concerned",
    "isOptOut": false
  },
  {
    "atomicId": "e697e813-c28e-47ef-b4e7-e93977c819aa",
    "phoneNumber": "16024187014",
    "receivedAt": "2026-02-09T20:35:09+00:00",
    "originalMessage": "Concern with rapid growth and unaffordable housing ",
    "atomicMessage": "Concern with unaffordable housing in the local area",
    "pollId": "019c29d4-81aa-733e-a72a-3983baf19a22",
    "clusterId": 6,
    "theme": "Affordable Housing Expansion",
    "category": "Housing",
    "summary": "Residents demand lower housing costs and rent protections to combat displacement caused by new population growth.",
    "sentiment": "concerned",
    "isOptOut": false
  },
  {
    "atomicId": "548bd60d-ee04-4448-b4f1-796570df3922",
    "phoneNumber": "12089015621",
    "receivedAt": "2026-02-09T21:42:32+00:00",
    "originalMessage": "STOP",
    "atomicMessage": "STOP",
    "pollId": "019c29d4-81aa-733e-a72a-3983baf19a22",
    "clusterId": "",
    "theme": "Opt Out Request",
    "category": "",
    "summary": "",
    "sentiment": "",
    "isOptOut": true
  },
  {
    "atomicId": "f343b7cb-0334-4925-aaeb-0918a124b60f",
    "phoneNumber": "12064320531",
    "receivedAt": "2026-02-09T22:37:32+00:00",
    "originalMessage": "More police to manage speeding. Drug use. Affordable housing",
    "atomicMessage": "Increase the presence of police officers to manage speeding and traffic safety in the local area.",
    "pollId": "019c29d4-81aa-733e-a72a-3983baf19a22",
    "clusterId": 2,
    "theme": "Traffic Congestion Management",
    "category": "Transportation",
    "summary": "Residents demand immediate action to reduce traffic volume and improve road safety through better infrastructure and enforcement.",
    "sentiment": "negative",
    "isOptOut": false
  },
  {
    "atomicId": "4d2cf0f7-6f45-400a-a105-3286ae549aa2",
    "phoneNumber": "12064320531",
    "receivedAt": "2026-02-09T22:37:32+00:00",
    "originalMessage": "More police to manage speeding. Drug use. Affordable housing",
    "atomicMessage": "Address the issues surrounding drug use and public health within the community.",
    "pollId": "019c29d4-81aa-733e-a72a-3983baf19a22",
    "clusterId": 8,
    "theme": "Community Safety Enhancements",
    "category": "Community Services",
    "summary": "Residents demand a comprehensive approach to public safety that combines park development with drug prevention and violence reduction.",
    "sentiment": "concerned",
    "isOptOut": false
  },
  {
    "atomicId": "1229f5e7-f68b-40f6-8a50-c2d4f77ef164",
    "phoneNumber": "12064320531",
    "receivedAt": "2026-02-09T22:37:32+00:00",
    "originalMessage": "More police to manage speeding. Drug use. Affordable housing",
    "atomicMessage": "Expand the availability of affordable housing options for residents in the area.",
    "pollId": "019c29d4-81aa-733e-a72a-3983baf19a22",
    "clusterId": 6,
    "theme": "Affordable Housing Expansion",
    "category": "Housing",
    "summary": "Residents demand lower housing costs and rent protections to combat displacement caused by new population growth.",
    "sentiment": "concerned",
    "isOptOut": false
  },
  {
    "atomicId": "c5f04286-cba6-4809-b055-a3a891dea23d",
    "phoneNumber": "18586990945",
    "receivedAt": "2026-02-09T23:09:31+00:00",
    "originalMessage": "Growth, infrastructure, water eg irrigation, schools",
    "atomicMessage": "The local area needs to address sustainable growth and urban development planning.",
    "pollId": "019c29d4-81aa-733e-a72a-3983baf19a22",
    "clusterId": 4,
    "theme": "Rapid Urban Overdevelopment",
    "category": "Housing",
    "summary": "Residents demand a halt to high-density construction to protect community character and prevent strain on public infrastructure.",
    "sentiment": "concerned",
    "isOptOut": false
  },
  {
    "atomicId": "bfc9b9e7-5ac6-4274-adb2-86cbddc204bb",
    "phoneNumber": "18586990945",
    "receivedAt": "2026-02-09T23:09:31+00:00",
    "originalMessage": "Growth, infrastructure, water eg irrigation, schools",
    "atomicMessage": "The community requires improvements and maintenance for public infrastructure.",
    "pollId": "019c29d4-81aa-733e-a72a-3983baf19a22",
    "clusterId": 0,
    "theme": "Infrastructure Maintenance",
    "category": "Infrastructure",
    "summary": "Residents demand immediate repairs to damaged roadways, safer cycling paths, and better management of invasive weeds on public sidewalks.",
    "sentiment": "negative",
    "isOptOut": false
  },
  {
    "atomicId": "535176ad-4a6d-413a-8209-9a09e7dde11a",
    "phoneNumber": "18586990945",
    "receivedAt": "2026-02-09T23:09:31+00:00",
    "originalMessage": "Growth, infrastructure, water eg irrigation, schools",
    "atomicMessage": "Water management and irrigation systems need to be prioritized for the area.",
    "pollId": "019c29d4-81aa-733e-a72a-3983baf19a22",
    "clusterId": 4,
    "theme": "Rapid Urban Overdevelopment",
    "category": "Housing",
    "summary": "Residents demand a halt to high-density construction to protect community character and prevent strain on public infrastructure.",
    "sentiment": "concerned",
    "isOptOut": false
  },
  {
    "atomicId": "d01a1ec2-ce9c-4406-8a41-724741c2e8df",
    "phoneNumber": "18586990945",
    "receivedAt": "2026-02-09T23:09:31+00:00",
    "originalMessage": "Growth, infrastructure, water eg irrigation, schools",
    "atomicMessage": "Local schools require additional support and resources for education.",
    "pollId": "019c29d4-81aa-733e-a72a-3983baf19a22",
    "clusterId": 1,
    "theme": "School Safety Measures",
    "category": "Education",
    "summary": "Constituents disagree on whether to deploy armed personnel within local schools to prevent violence.",
    "sentiment": "mixed",
    "isOptOut": false
  },
  {
    "atomicId": "f9b6bd92-8832-4c58-a034-f5a700f6e10b",
    "phoneNumber": "12085156733",
    "receivedAt": "2026-02-09T23:20:25+00:00",
    "originalMessage": "STOP",
    "atomicMessage": "STOP",
    "pollId": "019c29d4-81aa-733e-a72a-3983baf19a22",
    "clusterId": "",
    "theme": "Opt Out Request",
    "category": "",
    "summary": "",
    "sentiment": "",
    "isOptOut": true
  },
  {
    "atomicId": "788d7f12-8108-4da5-9cb9-421f8d749c0c",
    "phoneNumber": "12088703892",
    "receivedAt": "2026-02-10T00:05:50+00:00",
    "originalMessage": "STOP",
    "atomicMessage": "STOP",
    "pollId": "019c29d4-81aa-733e-a72a-3983baf19a22",
    "clusterId": "",
    "theme": "Opt Out Request",
    "category": "",
    "summary": "",
    "sentiment": "",
    "isOptOut": true
  },
  {
    "atomicId": "2354830c-372a-407c-9d02-3c564564cd76",
    "phoneNumber": "12082833262",
    "receivedAt": "2026-02-10T01:29:43+00:00",
    "originalMessage": "STOP ",
    "atomicMessage": "STOP ",
    "pollId": "019c29d4-81aa-733e-a72a-3983baf19a22",
    "clusterId": "",
    "theme": "Opt Out Request",
    "category": "",
    "summary": "",
    "sentiment": "",
    "isOptOut": true
  },
  {
    "atomicId": "38984cd2-a331-4184-aae4-cd342e2d1e28",
    "phoneNumber": "12088691778",
    "receivedAt": "2026-02-10T01:38:40+00:00",
    "originalMessage": "STOP",
    "atomicMessage": "STOP",
    "pollId": "019c29d4-81aa-733e-a72a-3983baf19a22",
    "clusterId": "",
    "theme": "Opt Out Request",
    "category": "",
    "summary": "",
    "sentiment": "",
    "isOptOut": true
  },
  {
    "atomicId": "89837465-d24b-4bef-be43-b939fdfc3f07",
    "phoneNumber": "18018228872",
    "receivedAt": "2026-02-10T03:18:21+00:00",
    "originalMessage": "STOP",
    "atomicMessage": "STOP",
    "pollId": "019c29d4-81aa-733e-a72a-3983baf19a22",
    "clusterId": "",
    "theme": "Opt Out Request",
    "category": "",
    "summary": "",
    "sentiment": "",
    "isOptOut": true
  },
  {
    "atomicId": "c779498c-f673-4ce8-be5b-ca8224f73823",
    "phoneNumber": "15035160678",
    "receivedAt": "2026-02-10T07:43:06+00:00",
    "originalMessage": "Stop population growth ",
    "atomicMessage": "The local area should implement policies to manage and limit population growth to ensure sustainable community development.",
    "pollId": "019c29d4-81aa-733e-a72a-3983baf19a22",
    "clusterId": 4,
    "theme": "Rapid Urban Overdevelopment",
    "category": "Housing",
    "summary": "Residents demand a halt to high-density construction to protect community character and prevent strain on public infrastructure.",
    "sentiment": "concerned",
    "isOptOut": false
  },
  {
    "atomicId": "d51b6e03-88e8-434f-a813-078ebf1f6264",
    "phoneNumber": "12089088031",
    "receivedAt": "2026-02-10T12:46:30+00:00",
    "originalMessage": "Traffic control and enforcement, managed growth and public transportation interests me. Thanks for asking.",
    "atomicMessage": "Traffic control and enforcement in the local area",
    "pollId": "019c29d4-81aa-733e-a72a-3983baf19a22",
    "clusterId": 2,
    "theme": "Traffic Congestion Management",
    "category": "Transportation",
    "summary": "Residents demand immediate action to reduce traffic volume and improve road safety through better infrastructure and enforcement.",
    "sentiment": "negative",
    "isOptOut": false
  },
  {
    "atomicId": "446bae2e-5921-4868-83c5-d12e8c5dce4b",
    "phoneNumber": "12089088031",
    "receivedAt": "2026-02-10T12:46:30+00:00",
    "originalMessage": "Traffic control and enforcement, managed growth and public transportation interests me. Thanks for asking.",
    "atomicMessage": "Managed growth within the community",
    "pollId": "019c29d4-81aa-733e-a72a-3983baf19a22",
    "clusterId": 4,
    "theme": "Rapid Urban Overdevelopment",
    "category": "Housing",
    "summary": "Residents demand a halt to high-density construction to protect community character and prevent strain on public infrastructure.",
    "sentiment": "concerned",
    "isOptOut": false
  },
  {
    "atomicId": "e9553be7-3b68-4c2e-84c0-2547c93b4ef3",
    "phoneNumber": "12089088031",
    "receivedAt": "2026-02-10T12:46:30+00:00",
    "originalMessage": "Traffic control and enforcement, managed growth and public transportation interests me. Thanks for asking.",
    "atomicMessage": "Public transportation interests and improvements",
    "pollId": "019c29d4-81aa-733e-a72a-3983baf19a22",
    "clusterId": 0,
    "theme": "Infrastructure Maintenance",
    "category": "Infrastructure",
    "summary": "Residents demand immediate repairs to damaged roadways, safer cycling paths, and better management of invasive weeds on public sidewalks.",
    "sentiment": "negative",
    "isOptOut": false
  },
  {
    "atomicId": "63f0ebdc-d7b7-4407-84e8-f5af59c2a07f",
    "phoneNumber": "12533152564",
    "receivedAt": "2026-02-11T01:31:11+00:00",
    "originalMessage": "Traffic on Ten Mile is horrible. We need improvements to infrastructure before MORE housing developments. \n\nWest ada school district is too huge. It should be cut in half at least! Kids aren't getting the attention from the district they need because it's oversized. ",
    "atomicMessage": "Traffic on Ten Mile is horrible.",
    "pollId": "019c29d4-81aa-733e-a72a-3983baf19a22",
    "clusterId": 2,
    "theme": "Traffic Congestion Management",
    "category": "Transportation",
    "summary": "Residents demand immediate action to reduce traffic volume and improve road safety through better infrastructure and enforcement.",
    "sentiment": "negative",
    "isOptOut": false
  },
  {
    "atomicId": "8b5a0008-1873-466c-865f-026dde989a50",
    "phoneNumber": "12533152564",
    "receivedAt": "2026-02-11T01:31:11+00:00",
    "originalMessage": "Traffic on Ten Mile is horrible. We need improvements to infrastructure before MORE housing developments. \n\nWest ada school district is too huge. It should be cut in half at least! Kids aren't getting the attention from the district they need because it's oversized. ",
    "atomicMessage": "The local area needs improvements to infrastructure.",
    "pollId": "019c29d4-81aa-733e-a72a-3983baf19a22",
    "clusterId": 0,
    "theme": "Infrastructure Maintenance",
    "category": "Infrastructure",
    "summary": "Residents demand immediate repairs to damaged roadways, safer cycling paths, and better management of invasive weeds on public sidewalks.",
    "sentiment": "negative",
    "isOptOut": false
  },
  {
    "atomicId": "c2c0e4d9-d5bb-42e9-a76c-d51a78ac6540",
    "phoneNumber": "12533152564",
    "receivedAt": "2026-02-11T01:31:11+00:00",
    "originalMessage": "Traffic on Ten Mile is horrible. We need improvements to infrastructure before MORE housing developments. \n\nWest ada school district is too huge. It should be cut in half at least! Kids aren't getting the attention from the district they need because it's oversized. ",
    "atomicMessage": "The local area should limit new housing developments.",
    "pollId": "019c29d4-81aa-733e-a72a-3983baf19a22",
    "clusterId": 4,
    "theme": "Rapid Urban Overdevelopment",
    "category": "Housing",
    "summary": "Residents demand a halt to high-density construction to protect community character and prevent strain on public infrastructure.",
    "sentiment": "concerned",
    "isOptOut": false
  },
  {
    "atomicId": "29ccccdd-6cd2-4c75-a172-bb425e2af7e5",
    "phoneNumber": "12533152564",
    "receivedAt": "2026-02-11T01:31:11+00:00",
    "originalMessage": "Traffic on Ten Mile is horrible. We need improvements to infrastructure before MORE housing developments. \n\nWest ada school district is too huge. It should be cut in half at least! Kids aren't getting the attention from the district they need because it's oversized. ",
    "atomicMessage": "The local school district is too large and should be divided.",
    "pollId": "019c29d4-81aa-733e-a72a-3983baf19a22",
    "clusterId": 1,
    "theme": "School Safety Measures",
    "category": "Education",
    "summary": "Constituents disagree on whether to deploy armed personnel within local schools to prevent violence.",
    "sentiment": "mixed",
    "isOptOut": false
  },
  {
    "atomicId": "fe863f96-b70c-4663-ae98-e842bb0f8f04",
    "phoneNumber": "12533152564",
    "receivedAt": "2026-02-11T01:31:11+00:00",
    "originalMessage": "Traffic on Ten Mile is horrible. We need improvements to infrastructure before MORE housing developments. \n\nWest ada school district is too huge. It should be cut in half at least! Kids aren't getting the attention from the district they need because it's oversized. ",
    "atomicMessage": "Students are not receiving adequate attention because the school district is oversized.",
    "pollId": "019c29d4-81aa-733e-a72a-3983baf19a22",
    "clusterId": 1,
    "theme": "School Safety Measures",
    "category": "Education",
    "summary": "Constituents disagree on whether to deploy armed personnel within local schools to prevent violence.",
    "sentiment": "mixed",
    "isOptOut": false
  },
  {
    "atomicId": "c9c7fea3-5323-494d-8925-1d31d22a1816",
    "phoneNumber": "12088663976",
    "receivedAt": "2026-02-11T14:19:31+00:00",
    "originalMessage": "Stop",
    "atomicMessage": "Stop",
    "pollId": "019c29d4-81aa-733e-a72a-3983baf19a22",
    "clusterId": "",
    "theme": "Opt Out Request",
    "category": "",
    "summary": "",
    "sentiment": "",
    "isOptOut": true
  }
]